[
  { "slug": "Opulent_Gloves", "name": "Opulent Gloves" },
  { "slug": "Omen_Sceptre", "name": "Omen Sceptre" },
  { "slug": "Lesser_Life_Flask", "name": "Lesser Life Flask" },
  { "slug": "Solar_Amulet", "name": "Solar Amulet" },
  { "slug": "Lesser_Mana_Flask", "name": "Lesser Mana Flask" },
  { "slug": "Tasalian_Focus", "name": "Tasalian Focus" },
  { "slug": "Sekhema_Sandals", "name": "Sekhema Sandals" },
  { "slug": "Ancestral_Tiara", "name": "Ancestral Tiara" },
  { "slug": "Pearl_Ring", "name": "Pearl Ring" },
  { "slug": "Fine_Belt", "name": "Fine Belt" },
  { "slug": "Champion_Cuirass", "name": "Champion Cuirass" },
  { "slug": "Utility_Belt", "name": "Utility Belt" },
  { "slug": "Tribal_Mask", "name": "Tribal Mask" },
  { "slug": "Sirenscale_Gloves", "name": "Sirenscale Gloves" },
  { "slug": "Ring", "name": "Ring" },
  { "slug": "Ashbark_Talisman", "name": "Ashbark Talisman" },
  { "slug": "Sacrificial_Regalia", "name": "Sacrificial Regalia" },
  { "slug": "Grand_Regalia", "name": "Grand Regalia" },
  { "slug": "Lapis_Amulet", "name": "Lapis Amulet" },
  { "slug": "Luxurious_Slippers", "name": "Luxurious Slippers" },
  { "slug": "Shrine_Sceptre", "name": "Shrine Sceptre" },
  { "slug": "Breach_Ring", "name": "Breach Ring" },
  { "slug": "Ultimate_Mana_Flask", "name": "Ultimate Mana Flask" },
  { "slug": "Grounding_Charm", "name": "Grounding Charm" },
  { "slug": "Thawing_Charm", "name": "Thawing Charm" },
  { "slug": "Ruby", "name": "Ruby", "cnName": "红玉" },
  { "slug": "Emerald", "name": "Emerald", "cnName": "翠玉" },
  { "slug": "Sapphire", "name": "Sapphire", "cnName": "蓝宝石" },
  { "slug": "Diamond", "name": "Diamond", "cnName": "宝钻" },
  { "slug": "Time-Lost_Ruby", "name": "Time-Lost Ruby", "cnName": "失落的红玉" },
  { "slug": "Time-Lost_Emerald", "name": "Time-Lost Emerald", "cnName": "失落的翠玉" },
  { "slug": "Time-Lost_Sapphire", "name": "Time-Lost Sapphire", "cnName": "失落的蓝宝石" },
  { "slug": "Time-Lost_Diamond", "name": "Time-Lost Diamond", "cnName": "失落的宝钻" },
  { "slug": "Timeless_Jewel", "name": "Timeless Jewel", "cnName": "永恒珠宝" }
]
